HISTORY.rst
MANIFEST.in
README.rst
requirements.txt
setup.cfg
setup.py
Afvaldienst/Afvaldienst.py
Afvaldienst/AfvaldienstScraper.py
Afvaldienst/__init__.py
Afvaldienst/test_afvalstoffendienstkalender.py
Afvaldienst/test_afvalstoffendienstkalender_scraper.py
Afvaldienst/test_mijnafvalwijzer.py
Afvaldienst/test_mijnafvalwijzer_scraper.py
afvaldienst.egg-info/PKG-INFO
afvaldienst.egg-info/SOURCES.txt
afvaldienst.egg-info/dependency_links.txt
afvaldienst.egg-info/not-zip-safe
afvaldienst.egg-info/requires.txt
afvaldienst.egg-info/top_level.txt