Metadata-Version: 2.1
Name: afvaldienst
Version: 1.1.4
Summary: Getting information on trash for the Netherlands for mijnafvalwijzer.nl and afvalstoffendienstkalender.nl
Home-page: https://github.com/xirixiz/afvaldienst
Author: Bram van Dartel
Author-email: spam@rootrulez.com
License: MIT
Keywords: afval afvaldienst afvalwijzer garbage trash mijnafvalwijzer afvalstoffendienstkalender dutch
Platform: UNKNOWN
Classifier: License :: OSI Approved :: MIT License
Classifier: Intended Audience :: End Users/Desktop
Classifier: Intended Audience :: Other Audience
Classifier: Programming Language :: Python
Classifier: Programming Language :: Python :: 2.7
Classifier: Programming Language :: Python :: 3.4
Classifier: Programming Language :: Python :: 3.5
Classifier: Programming Language :: Python :: 3.6
Classifier: Programming Language :: Python :: 3.7
Classifier: Programming Language :: Python :: 3.8
Classifier: Natural Language :: English
Classifier: Natural Language :: Dutch
Classifier: License :: OSI Approved :: MIT License
Classifier: Operating System :: Unix
Classifier: Operating System :: MacOS
Classifier: Operating System :: Microsoft :: Windows
Classifier: Topic :: Software Development :: Libraries :: Python Modules
